[
  {
    "id": "18024517709227640",
    "text": "😍😍😍",
    "created_at": 1730135376,
    "did_report_as_spam": false,
    "owner": {
      "id": "17423409856",
      "is_verified": false,
      "profile_pic_url": "https://scontent-lga3-2.cdninstagram.com/v/t51.2885-19/539484175_18105076975577857_1858409124179547435_n.jpg?stp=dst-jpg_e0_s150x150_tt6&efg=eyJ2ZW5jb2RlX3RhZyI6InByb2ZpbGVfcGljLmRqYW5nby4xMDgwLmMyIn0&_nc_ht=scontent-lga3-2.cdninstagram.com&_nc_cat=101&_nc_oc=Q6cZ2QE9FuvkGCl951PjJHammTzf3z5nc8bcOqhVLS6WtNLFuO_Enimyho8bpT7vg6hHLfs&_nc_ohc=LLKjPJAcS0MQ7kNvwGyudJW&_nc_gid=e8FEGUr_AuSr0AbTU1bNNw&edm=AMrZAGUBAAAA&ccb=7-5&oh=00_AfecsSlOBLE1yro_SNwviZFDZ5kZPwu6Gqz5pmJZY_4NUQ&oe=69060CA2&_nc_sid=17eaee",
      "username": "mr_himanshu____98"
    },
    "likes": 1,
    "comments": 0
  },
  {
    "id": "17914138383002004",
    "text": "🔥🔥🔥",
    "created_at": 1730135375,
    "did_report_as_spam": false,
    "owner": {
      "id": "17423409856",
      "is_verified": false,
      "profile_pic_url": "https://scontent-lga3-2.cdninstagram.com/v/t51.2885-19/539484175_18105076975577857_1858409124179547435_n.jpg?stp=dst-jpg_e0_s150x150_tt6&efg=eyJ2ZW5jb2RlX3RhZyI6InByb2ZpbGVfcGljLmRqYW5nby4xMDgwLmMyIn0&_nc_ht=scontent-lga3-2.cdninstagram.com&_nc_cat=101&_nc_oc=Q6cZ2QE9FuvkGCl951PjJHammTzf3z5nc8bcOqhVLS6WtNLFuO_Enimyho8bpT7vg6hHLfs&_nc_ohc=LLKjPJAcS0MQ7kNvwGyudJW&_nc_gid=e8FEGUr_AuSr0AbTU1bNNw&edm=AMrZAGUBAAAA&ccb=7-5&oh=00_AfecsSlOBLE1yro_SNwviZFDZ5kZPwu6Gqz5pmJZY_4NUQ&oe=69060CA2&_nc_sid=17eaee",
      "username": "mr_himanshu____98"
    },
    "likes": 1,
    "comments": 0
  },
  {
    "id": "18055959424857010",
    "text": "❤❤❤️",
    "created_at": 1730135374,
    "did_report_as_spam": false,
    "owner": {
      "id": "17423409856",
      "is_verified": false,
      "profile_pic_url": "https://scontent-lga3-2.cdninstagram.com/v/t51.2885-19/539484175_18105076975577857_1858409124179547435_n.jpg?stp=dst-jpg_e0_s150x150_tt6&efg=eyJ2ZW5jb2RlX3RhZyI6InByb2ZpbGVfcGljLmRqYW5nby4xMDgwLmMyIn0&_nc_ht=scontent-lga3-2.cdninstagram.com&_nc_cat=101&_nc_oc=Q6cZ2QE9FuvkGCl951PjJHammTzf3z5nc8bcOqhVLS6WtNLFuO_Enimyho8bpT7vg6hHLfs&_nc_ohc=LLKjPJAcS0MQ7kNvwGyudJW&_nc_gid=e8FEGUr_AuSr0AbTU1bNNw&edm=AMrZAGUBAAAA&ccb=7-5&oh=00_AfecsSlOBLE1yro_SNwviZFDZ5kZPwu6Gqz5pmJZY_4NUQ&oe=69060CA2&_nc_sid=17eaee",
      "username": "mr_himanshu____98"
    },
    "likes": 1,
    "comments": 0
  },
  {
    "id": "18077630563497826",
    "text": "🔥🔥❤️",
    "created_at": 1729416219,
    "did_report_as_spam": false,
    "owner": {
      "id": "52989390194",
      "is_verified": false,
      "profile_pic_url": "https://scontent-lga3-1.cdninstagram.com/v/t51.2885-19/470481748_4000167653588831_2036151453631741386_n.jpg?stp=dst-jpg_e0_s150x150_tt6&efg=eyJ2ZW5jb2RlX3RhZyI6InByb2ZpbGVfcGljLmRqYW5nby4xMDcwLmMyIn0&_nc_ht=scontent-lga3-1.cdninstagram.com&_nc_cat=111&_nc_oc=Q6cZ2QE9FuvkGCl951PjJHammTzf3z5nc8bcOqhVLS6WtNLFuO_Enimyho8bpT7vg6hHLfs&_nc_ohc=DRGQJV3L4nQQ7kNvwHSXMCQ&_nc_gid=e8FEGUr_AuSr0AbTU1bNNw&edm=AMrZAGUBAAAA&ccb=7-5&oh=00_AfeBgEgfj8wKgkFHAR51R7kZVjocvbImmn6I6NKChLGd6w&oe=69062669&_nc_sid=17eaee",
      "username": "kranti_patil2584"
    },
    "likes": 2,
    "comments": 1
  },
  {
    "id": "18071692087611586",
    "text": "🔥🔥",
    "created_at": 1729410848,
    "did_report_as_spam": false,
    "owner": {
      "id": "53525685757",
      "is_verified": false,
      "profile_pic_url": "https://scontent-lga3-3.cdninstagram.com/v/t51.2885-19/548877744_18010191467789758_1354609975233728845_n.jpg?stp=dst-jpg_e0_s150x150_tt6&efg=eyJ2ZW5jb2RlX3RhZyI6InByb2ZpbGVfcGljLmRqYW5nby4xMDgwLmMyIn0&_nc_ht=scontent-lga3-3.cdninstagram.com&_nc_cat=110&_nc_oc=Q6cZ2QE9FuvkGCl951PjJHammTzf3z5nc8bcOqhVLS6WtNLFuO_Enimyho8bpT7vg6hHLfs&_nc_ohc=K6lzx9rkFOMQ7kNvwG3a5lu&_nc_gid=e8FEGUr_AuSr0AbTU1bNNw&edm=AMrZAGUBAAAA&ccb=7-5&oh=00_AfcE4gKlkK0l1OMQJ-NPJvmK0RsxoLiY6Nmu5kGcNZdNXA&oe=69061DF5&_nc_sid=17eaee",
      "username": "viishhh_22"
    },
    "likes": 1,
    "comments": 0
  },
  {
    "id": "18044587550015559",
    "text": "🔥🔥",
    "created_at": 1729406460,
    "did_report_as_spam": false,
    "owner": {
      "id": "6915208072",
      "is_verified": false,
      "profile_pic_url": "https://scontent-lga3-2.cdninstagram.com/v/t51.2885-19/469951702_1577071259847369_5912950441966077759_n.jpg?stp=dst-jpg_e0_s150x150_tt6&efg=eyJ2ZW5jb2RlX3RhZyI6InByb2ZpbGVfcGljLmRqYW5nby4xMDgwLmMyIn0&_nc_ht=scontent-lga3-2.cdninstagram.com&_nc_cat=109&_nc_oc=Q6cZ2QE9FuvkGCl951PjJHammTzf3z5nc8bcOqhVLS6WtNLFuO_Enimyho8bpT7vg6hHLfs&_nc_ohc=rYcarQQmAnwQ7kNvwFwm_GS&_nc_gid=e8FEGUr_AuSr0AbTU1bNNw&edm=AMrZAGUBAAAA&ccb=7-5&oh=00_Afd409sT1CQQoKcl1gCIgU0ua_gsp-3lxK9KcYmYSbUcsg&oe=690606C6&_nc_sid=17eaee",
      "username": "_albatross_0_1_7"
    },
    "likes": 1,
    "comments": 0
  },
  {
    "id": "18083146285469793",
    "text": "🙌🔥",
    "created_at": 1729400098,
    "did_report_as_spam": false,
    "owner": {
      "id": "48834624862",
      "is_verified": false,
      "profile_pic_url": "https://scontent-lga3-2.cdninstagram.com/v/t51.2885-19/564881194_18063342947624863_5485997861462772160_n.jpg?stp=dst-jpg_e0_s150x150_tt6&efg=eyJ2ZW5jb2RlX3RhZyI6InByb2ZpbGVfcGljLmRqYW5nby4xMDgwLmMyIn0&_nc_ht=scontent-lga3-2.cdninstagram.com&_nc_cat=107&_nc_oc=Q6cZ2QE9FuvkGCl951PjJHammTzf3z5nc8bcOqhVLS6WtNLFuO_Enimyho8bpT7vg6hHLfs&_nc_ohc=eFXTto2aLJ0Q7kNvwE_iA2R&_nc_gid=e8FEGUr_AuSr0AbTU1bNNw&edm=AMrZAGUBAAAA&ccb=7-5&oh=00_Afe4SAuI4wLd_q_mGDfQigPgqFdfRNxRnRLOYkBbKHtyUg&oe=69062E4E&_nc_sid=17eaee",
      "username": "m_hai_ham___"
    },
    "likes": 1,
    "comments": 0
  },
  {
    "id": "18063925876709280",
    "text": "🔥❤️",
    "created_at": 1729399677,
    "did_report_as_spam": false,
    "owner": {
      "id": "31795413335",
      "is_verified": false,
      "profile_pic_url": "https://scontent-lga3-2.cdninstagram.com/v/t51.2885-19/569171843_18079837604061336_2167527024408385230_n.jpg?stp=dst-jpg_e0_s150x150_tt6&efg=eyJ2ZW5jb2RlX3RhZyI6InByb2ZpbGVfcGljLmRqYW5nby4xMDgwLmMyIn0&_nc_ht=scontent-lga3-2.cdninstagram.com&_nc_cat=100&_nc_oc=Q6cZ2QE9FuvkGCl951PjJHammTzf3z5nc8bcOqhVLS6WtNLFuO_Enimyho8bpT7vg6hHLfs&_nc_ohc=VMqjNeUhh2IQ7kNvwGQ64wG&_nc_gid=e8FEGUr_AuSr0AbTU1bNNw&edm=AMrZAGUBAAAA&ccb=7-5&oh=00_Afc9k3MB6h7KsAPcFGY83BgzTVB6bxVj5aV1Y-RD5-KlPg&oe=6905FC57&_nc_sid=17eaee",
      "username": "parthmandore"
    },
    "likes": 1,
    "comments": 0
  },
  {
    "id": "18469237939060304",
    "text": "Chora khali chori patata hai 😂",
    "created_at": 1729399480,
    "did_report_as_spam": false,
    "owner": {
      "id": "20326122165",
      "is_verified": false,
      "profile_pic_url": "https://scontent-lga3-3.cdninstagram.com/v/t51.2885-19/512175264_18086455252674166_2480273853729116536_n.jpg?stp=dst-jpg_e0_s150x150_tt6&efg=eyJ2ZW5jb2RlX3RhZyI6InByb2ZpbGVfcGljLmRqYW5nby4xMDgwLmMyIn0&_nc_ht=scontent-lga3-3.cdninstagram.com&_nc_cat=110&_nc_oc=Q6cZ2QE9FuvkGCl951PjJHammTzf3z5nc8bcOqhVLS6WtNLFuO_Enimyho8bpT7vg6hHLfs&_nc_ohc=dfAHXIb_D5AQ7kNvwEGw6TK&_nc_gid=e8FEGUr_AuSr0AbTU1bNNw&edm=AMrZAGUBAAAA&ccb=7-5&oh=00_AfeKKX4fRcEMvTQwZ-_E9pEBZQGyvlUXqHWfGUTgXX7_wA&oe=69061990&_nc_sid=17eaee",
      "username": "mr_saket_"
    },
    "likes": 1,
    "comments": 1
  },
  {
    "id": "18040729270901810",
    "text": "🔋❣️",
    "created_at": 1729398440,
    "did_report_as_spam": false,
    "owner": {
      "id": "63204862794",
      "is_verified": false,
      "profile_pic_url": "https://scontent-lga3-1.cdninstagram.com/v/t51.2885-19/540989133_17922874521110795_3682156022363909977_n.jpg?stp=dst-jpg_e0_s150x150_tt6&efg=eyJ2ZW5jb2RlX3RhZyI6InByb2ZpbGVfcGljLmRqYW5nby4xMDgwLmMyIn0&_nc_ht=scontent-lga3-1.cdninstagram.com&_nc_cat=111&_nc_oc=Q6cZ2QE9FuvkGCl951PjJHammTzf3z5nc8bcOqhVLS6WtNLFuO_Enimyho8bpT7vg6hHLfs&_nc_ohc=8nZ37OtdLTQQ7kNvwExtCEO&_nc_gid=e8FEGUr_AuSr0AbTU1bNNw&edm=AMrZAGUBAAAA&ccb=7-5&oh=00_AfeRUZN34UomjmCMj0bZgPE-BgvtV02xR7gcHf8vWMxAMQ&oe=69061967&_nc_sid=17eaee",
      "username": "dpushkarx26"
    },
    "likes": 1,
    "comments": 0
  },
  {
    "id": "18044702150009452",
    "text": "🔥🔥🔥❤️",
    "created_at": 1729397685,
    "did_report_as_spam": false,
    "owner": {
      "id": "36726104452",
      "is_verified": false,
      "profile_pic_url": "https://scontent-lga3-2.cdninstagram.com/v/t51.2885-19/519157862_18061086416224453_2799902721608634294_n.jpg?stp=dst-jpg_e0_s150x150_tt6&efg=eyJ2ZW5jb2RlX3RhZyI6InByb2ZpbGVfcGljLmRqYW5nby4xMDgwLmMyIn0&_nc_ht=scontent-lga3-2.cdninstagram.com&_nc_cat=101&_nc_oc=Q6cZ2QE9FuvkGCl951PjJHammTzf3z5nc8bcOqhVLS6WtNLFuO_Enimyho8bpT7vg6hHLfs&_nc_ohc=AZTiHmN8yNYQ7kNvwGUbbF7&_nc_gid=e8FEGUr_AuSr0AbTU1bNNw&edm=AMrZAGUBAAAA&ccb=7-5&oh=00_AfcKtOwqhbjSsIVxPnuOGp2obe7T6I6wVG9EMVxBOruhQg&oe=69062B1F&_nc_sid=17eaee",
      "username": "patil_mitanshu_"
    },
    "likes": 1,
    "comments": 0
  },
  {
    "id": "18359486464140513",
    "text": "🔥🔥🙌",
    "created_at": 1729396180,
    "did_report_as_spam": false,
    "owner": {
      "id": "38933104702",
      "is_verified": false,
      "profile_pic_url": "https://scontent-lga3-1.cdninstagram.com/v/t51.2885-19/566207549_18082276721296703_1707161293386333706_n.jpg?stp=dst-jpg_e0_s150x150_tt6&efg=eyJ2ZW5jb2RlX3RhZyI6InByb2ZpbGVfcGljLmRqYW5nby4xMDc4LmMyIn0&_nc_ht=scontent-lga3-1.cdninstagram.com&_nc_cat=111&_nc_oc=Q6cZ2QE9FuvkGCl951PjJHammTzf3z5nc8bcOqhVLS6WtNLFuO_Enimyho8bpT7vg6hHLfs&_nc_ohc=feiTdtyHbPkQ7kNvwGhYK_B&_nc_gid=e8FEGUr_AuSr0AbTU1bNNw&edm=AMrZAGUBAAAA&ccb=7-5&oh=00_AffUmwG9zslUhFactboBLnOgI14gOCrzUwuXE-dgcOma-Q&oe=6905FF44&_nc_sid=17eaee",
      "username": "yogesh_pardeshi_yp"
    },
    "likes": 1,
    "comments": 0
  },
  {
    "id": "18063442483675647",
    "text": "🔥🔥",
    "created_at": 1729395160,
    "did_report_as_spam": false,
    "owner": {
      "id": "38468682309",
      "is_verified": false,
      "profile_pic_url": "https://scontent-lga3-2.cdninstagram.com/v/t51.2885-19/488016940_2317371501979889_5020868443498003834_n.jpg?stp=dst-jpg_e0_s150x150_tt6&efg=eyJ2ZW5jb2RlX3RhZyI6InByb2ZpbGVfcGljLmRqYW5nby45MDQuYzIifQ&_nc_ht=scontent-lga3-2.cdninstagram.com&_nc_cat=105&_nc_oc=Q6cZ2QE9FuvkGCl951PjJHammTzf3z5nc8bcOqhVLS6WtNLFuO_Enimyho8bpT7vg6hHLfs&_nc_ohc=MGuXy4uNgF0Q7kNvwGPhyhc&_nc_gid=e8FEGUr_AuSr0AbTU1bNNw&edm=AMrZAGUBAAAA&ccb=7-5&oh=00_Afd9reO0KA68tYyWUhIPFMsg10HCXkxZ9gZlcTIRVymEOg&oe=69060400&_nc_sid=17eaee",
      "username": "pawan.shimpi.737"
    },
    "likes": 1,
    "comments": 0
  },
  {
    "id": "18023623850233965",
    "text": "🔥🔥🔥",
    "created_at": 1729394602,
    "did_report_as_spam": false,
    "owner": {
      "id": "1645572378",
      "is_verified": false,
      "profile_pic_url": "https://scontent-lga3-3.cdninstagram.com/v/t51.2885-19/299377326_629058641884948_6971824716837449980_n.jpg?stp=dst-jpg_e0_s150x150_tt6&efg=eyJ2ZW5jb2RlX3RhZyI6InByb2ZpbGVfcGljLmRqYW5nby41NTQuYzIifQ&_nc_ht=scontent-lga3-3.cdninstagram.com&_nc_cat=104&_nc_oc=Q6cZ2QE9FuvkGCl951PjJHammTzf3z5nc8bcOqhVLS6WtNLFuO_Enimyho8bpT7vg6hHLfs&_nc_ohc=20yW35RQgb0Q7kNvwEmuE0Q&_nc_gid=e8FEGUr_AuSr0AbTU1bNNw&edm=AMrZAGUBAAAA&ccb=7-5&oh=00_AfcLLUuU2vj6LqTvH6r_ohaEMhQ_1Hh1SZCzW-7ndpQjkg&oe=69061B73&_nc_sid=17eaee",
      "username": "chetan.bhadane78"
    },
    "likes": 1,
    "comments": 1
  },
  {
    "id": "18060800428705064",
    "text": "🔥🔥🙌",
    "created_at": 1729394463,
    "did_report_as_spam": false,
    "owner": {
      "id": "51238449165",
      "is_verified": false,
      "profile_pic_url": "https://scontent-lga3-3.cdninstagram.com/v/t51.2885-19/561838510_18039299873705166_2679877730098420832_n.jpg?stp=dst-jpg_e0_s150x150_tt6&efg=eyJ2ZW5jb2RlX3RhZyI6InByb2ZpbGVfcGljLmRqYW5nby4xMDgwLmMyIn0&_nc_ht=scontent-lga3-3.cdninstagram.com&_nc_cat=106&_nc_oc=Q6cZ2QE9FuvkGCl951PjJHammTzf3z5nc8bcOqhVLS6WtNLFuO_Enimyho8bpT7vg6hHLfs&_nc_ohc=iVhdXIo7msAQ7kNvwFPQe_c&_nc_gid=e8FEGUr_AuSr0AbTU1bNNw&edm=AMrZAGUBAAAA&ccb=7-5&oh=00_AfeBMPzMCUME1Be99V9lNZF69NX1_QRIR8UKLDc7M5xF_g&oe=69062AC4&_nc_sid=17eaee",
      "username": "lokessh__07"
    },
    "likes": 1,
    "comments": 0
  }
]